<?xml version='1.0' encoding='utf-8'?>
<graphml xmlns="http://graphml.graphdrawing.org/xmlns" xmlns:xsi="http://www.w3.org/2001/XMLSchema-instance" xsi:schemaLocation="http://graphml.graphdrawing.org/xmlns http://graphml.graphdrawing.org/xmlns/1.0/graphml.xsd">
  <key attr.name="weight" attr.type="double" for="edge" id="d0" />
  <graph edgedefault="undirected">
    <node id="0" />
    <node id="1" />
    <node id="2" />
    <node id="3" />
    <node id="4" />
    <node id="5" />
    <node id="6" />
    <node id="7" />
    <node id="8" />
    <node id="9" />
    <node id="10" />
    <node id="11" />
    <node id="12" />
    <node id="13" />
    <node id="14" />
    <node id="15" />
    <node id="16" />
    <node id="17" />
    <node id="18" />
    <node id="19" />
    <node id="20" />
    <node id="21" />
    <node id="22" />
    <node id="23" />
    <node id="24" />
    <node id="25" />
    <node id="26" />
    <node id="27" />
    <node id="28" />
    <node id="29" />
    <node id="30" />
    <node id="31" />
    <node id="32" />
    <node id="33" />
    <node id="34" />
    <node id="35" />
    <node id="36" />
    <node id="37" />
    <node id="38" />
    <node id="39" />
    <node id="40" />
    <node id="41" />
    <node id="42" />
    <node id="43" />
    <node id="44" />
    <node id="45" />
    <node id="46" />
    <node id="47" />
    <node id="48" />
    <node id="49" />
    <node id="50" />
    <node id="51" />
    <node id="52" />
    <node id="53" />
    <node id="54" />
    <node id="55" />
    <node id="56" />
    <node id="57" />
    <node id="58" />
    <node id="59" />
    <node id="60" />
    <node id="61" />
    <node id="62" />
    <node id="63" />
    <node id="64" />
    <node id="65" />
    <node id="66" />
    <node id="67" />
    <node id="68" />
    <node id="69" />
    <node id="70" />
    <node id="71" />
    <node id="72" />
    <node id="73" />
    <node id="74" />
    <node id="75" />
    <node id="76" />
    <node id="77" />
    <node id="78" />
    <node id="79" />
    <node id="80" />
    <node id="81" />
    <node id="82" />
    <node id="83" />
    <node id="84" />
    <edge source="0" target="6">
      <data key="d0">0.558501</data>
    </edge>
    <edge source="0" target="35">
      <data key="d0">0.402936</data>
    </edge>
    <edge source="0" target="36">
      <data key="d0">0.556251</data>
    </edge>
    <edge source="0" target="40">
      <data key="d0">0.424517</data>
    </edge>
    <edge source="0" target="48">
      <data key="d0">0.565696</data>
    </edge>
    <edge source="0" target="59">
      <data key="d0">0.452557</data>
    </edge>
    <edge source="0" target="60">
      <data key="d0">0.335233</data>
    </edge>
    <edge source="0" target="73">
      <data key="d0">0.293736</data>
    </edge>
    <edge source="0" target="78">
      <data key="d0">0.324919</data>
    </edge>
    <edge source="0" target="83">
      <data key="d0">0.520996</data>
    </edge>
    <edge source="1" target="6">
      <data key="d0">0.583378</data>
    </edge>
    <edge source="1" target="7">
      <data key="d0">0.560825</data>
    </edge>
    <edge source="1" target="35">
      <data key="d0">0.390189</data>
    </edge>
    <edge source="1" target="36">
      <data key="d0">0.574648</data>
    </edge>
    <edge source="1" target="40">
      <data key="d0">0.495262</data>
    </edge>
    <edge source="1" target="48">
      <data key="d0">0.479913</data>
    </edge>
    <edge source="1" target="59">
      <data key="d0">0.504731</data>
    </edge>
    <edge source="1" target="60">
      <data key="d0">0.328884</data>
    </edge>
    <edge source="1" target="73">
      <data key="d0">0.284236</data>
    </edge>
    <edge source="1" target="78">
      <data key="d0">0.338709</data>
    </edge>
    <edge source="1" target="83">
      <data key="d0">0.548728</data>
    </edge>
    <edge source="2" target="35">
      <data key="d0">0.368019</data>
    </edge>
    <edge source="2" target="36">
      <data key="d0">0.593101</data>
    </edge>
    <edge source="2" target="40">
      <data key="d0">0.534559</data>
    </edge>
    <edge source="2" target="48">
      <data key="d0">0.527275</data>
    </edge>
    <edge source="2" target="59">
      <data key="d0">0.512781</data>
    </edge>
    <edge source="2" target="60">
      <data key="d0">0.32309</data>
    </edge>
    <edge source="2" target="73">
      <data key="d0">0.26435</data>
    </edge>
    <edge source="2" target="78">
      <data key="d0">0.363411</data>
    </edge>
    <edge source="2" target="83">
      <data key="d0">0.536766</data>
    </edge>
    <edge source="3" target="6">
      <data key="d0">0.56225</data>
    </edge>
    <edge source="3" target="7">
      <data key="d0">0.58991</data>
    </edge>
    <edge source="3" target="30">
      <data key="d0">0.508819</data>
    </edge>
    <edge source="3" target="34">
      <data key="d0">0.532522</data>
    </edge>
    <edge source="3" target="35">
      <data key="d0">0.343484</data>
    </edge>
    <edge source="3" target="36">
      <data key="d0">0.543632</data>
    </edge>
    <edge source="3" target="40">
      <data key="d0">0.494744</data>
    </edge>
    <edge source="3" target="48">
      <data key="d0">0.463234</data>
    </edge>
    <edge source="3" target="59">
      <data key="d0">0.516559</data>
    </edge>
    <edge source="3" target="60">
      <data key="d0">0.28733</data>
    </edge>
    <edge source="3" target="73">
      <data key="d0">0.269262</data>
    </edge>
    <edge source="3" target="78">
      <data key="d0">0.389581</data>
    </edge>
    <edge source="3" target="83">
      <data key="d0">0.505854</data>
    </edge>
    <edge source="4" target="6">
      <data key="d0">0.57868</data>
    </edge>
    <edge source="4" target="28">
      <data key="d0">0.592768</data>
    </edge>
    <edge source="4" target="30">
      <data key="d0">0.570908</data>
    </edge>
    <edge source="4" target="35">
      <data key="d0">0.363819</data>
    </edge>
    <edge source="4" target="40">
      <data key="d0">0.473436</data>
    </edge>
    <edge source="4" target="48">
      <data key="d0">0.498176</data>
    </edge>
    <edge source="4" target="59">
      <data key="d0">0.433867</data>
    </edge>
    <edge source="4" target="60">
      <data key="d0">0.348263</data>
    </edge>
    <edge source="4" target="73">
      <data key="d0">0.348168</data>
    </edge>
    <edge source="4" target="78">
      <data key="d0">0.385705</data>
    </edge>
    <edge source="4" target="79">
      <data key="d0">0.568908</data>
    </edge>
    <edge source="4" target="83">
      <data key="d0">0.444357</data>
    </edge>
    <edge source="5" target="6">
      <data key="d0">0.50439</data>
    </edge>
    <edge source="5" target="30">
      <data key="d0">0.513662</data>
    </edge>
    <edge source="5" target="34">
      <data key="d0">0.584246</data>
    </edge>
    <edge source="5" target="35">
      <data key="d0">0.311978</data>
    </edge>
    <edge source="5" target="40">
      <data key="d0">0.493028</data>
    </edge>
    <edge source="5" target="48">
      <data key="d0">0.591103</data>
    </edge>
    <edge source="5" target="59">
      <data key="d0">0.543046</data>
    </edge>
    <edge source="5" target="60">
      <data key="d0">0.358832</data>
    </edge>
    <edge source="5" target="73">
      <data key="d0">0.39642</data>
    </edge>
    <edge source="5" target="74">
      <data key="d0">0.528164</data>
    </edge>
    <edge source="5" target="77">
      <data key="d0">0.591938</data>
    </edge>
    <edge source="5" target="78">
      <data key="d0">0.372048</data>
    </edge>
    <edge source="5" target="80">
      <data key="d0">0.587707</data>
    </edge>
    <edge source="5" target="83">
      <data key="d0">0.454636</data>
    </edge>
    <edge source="6" target="7">
      <data key="d0">0.214973</data>
    </edge>
    <edge source="6" target="8">
      <data key="d0">0.519579</data>
    </edge>
    <edge source="6" target="9">
      <data key="d0">0.343754</data>
    </edge>
    <edge source="6" target="10">
      <data key="d0">0.443256</data>
    </edge>
    <edge source="6" target="13">
      <data key="d0">0.518656</data>
    </edge>
    <edge source="6" target="14">
      <data key="d0">0.385055</data>
    </edge>
    <edge source="6" target="15">
      <data key="d0">0.584461</data>
    </edge>
    <edge source="6" target="16">
      <data key="d0">0.508377</data>
    </edge>
    <edge source="6" target="19">
      <data key="d0">0.585739</data>
    </edge>
    <edge source="6" target="20">
      <data key="d0">0.556901</data>
    </edge>
    <edge source="6" target="21">
      <data key="d0">0.377886</data>
    </edge>
    <edge source="6" target="22">
      <data key="d0">0.548055</data>
    </edge>
    <edge source="6" target="23">
      <data key="d0">0.548414</data>
    </edge>
    <edge source="6" target="24">
      <data key="d0">0.463656</data>
    </edge>
    <edge source="6" target="25">
      <data key="d0">0.504748</data>
    </edge>
    <edge source="6" target="26">
      <data key="d0">0.578286</data>
    </edge>
    <edge source="6" target="28">
      <data key="d0">0.373706</data>
    </edge>
    <edge source="6" target="29">
      <data key="d0">0.39659</data>
    </edge>
    <edge source="6" target="30">
      <data key="d0">0.557769</data>
    </edge>
    <edge source="6" target="31">
      <data key="d0">0.528169</data>
    </edge>
    <edge source="6" target="34">
      <data key="d0">0.517268</data>
    </edge>
    <edge source="6" target="35">
      <data key="d0">0.386064</data>
    </edge>
    <edge source="6" target="36">
      <data key="d0">0.369013</data>
    </edge>
    <edge source="6" target="37">
      <data key="d0">0.316127</data>
    </edge>
    <edge source="6" target="38">
      <data key="d0">0.556713</data>
    </edge>
    <edge source="6" target="39">
      <data key="d0">0.569491</data>
    </edge>
    <edge source="6" target="40">
      <data key="d0">0.251821</data>
    </edge>
    <edge source="6" target="41">
      <data key="d0">0.351075</data>
    </edge>
    <edge source="6" target="43">
      <data key="d0">0.582114</data>
    </edge>
    <edge source="6" target="44">
      <data key="d0">0.583656</data>
    </edge>
    <edge source="6" target="45">
      <data key="d0">0.580929</data>
    </edge>
    <edge source="6" target="46">
      <data key="d0">0.432607</data>
    </edge>
    <edge source="6" target="48">
      <data key="d0">0.347918</data>
    </edge>
    <edge source="6" target="49">
      <data key="d0">0.49228</data>
    </edge>
    <edge source="6" target="52">
      <data key="d0">0.583582</data>
    </edge>
    <edge source="6" target="55">
      <data key="d0">0.580897</data>
    </edge>
    <edge source="6" target="56">
      <data key="d0">0.556748</data>
    </edge>
    <edge source="6" target="58">
      <data key="d0">0.525589</data>
    </edge>
    <edge source="6" target="59">
      <data key="d0">0.351319</data>
    </edge>
    <edge source="6" target="60">
      <data key="d0">0.274141</data>
    </edge>
    <edge source="6" target="63">
      <data key="d0">0.560778</data>
    </edge>
    <edge source="6" target="64">
      <data key="d0">0.542391</data>
    </edge>
    <edge source="6" target="65">
      <data key="d0">0.379905</data>
    </edge>
    <edge source="6" target="67">
      <data key="d0">0.572449</data>
    </edge>
    <edge source="6" target="70">
      <data key="d0">0.590657</data>
    </edge>
    <edge source="6" target="72">
      <data key="d0">0.262233</data>
    </edge>
    <edge source="6" target="73">
      <data key="d0">0.16263</data>
    </edge>
    <edge source="6" target="74">
      <data key="d0">0.58986</data>
    </edge>
    <edge source="6" target="78">
      <data key="d0">0.287594</data>
    </edge>
    <edge source="6" target="79">
      <data key="d0">0.56107</data>
    </edge>
    <edge source="6" target="80">
      <data key="d0">0.462322</data>
    </edge>
    <edge source="6" target="81">
      <data key="d0">0.586169</data>
    </edge>
    <edge source="6" target="82">
      <data key="d0">0.584076</data>
    </edge>
    <edge source="6" target="83">
      <data key="d0">0.516437</data>
    </edge>
    <edge source="6" target="84">
      <data key="d0">0.301239</data>
    </edge>
    <edge source="7" target="8">
      <data key="d0">0.542867</data>
    </edge>
    <edge source="7" target="9">
      <data key="d0">0.36722</data>
    </edge>
    <edge source="7" target="10">
      <data key="d0">0.545505</data>
    </edge>
    <edge source="7" target="11">
      <data key="d0">0.413538</data>
    </edge>
    <edge source="7" target="14">
      <data key="d0">0.486644</data>
    </edge>
    <edge source="7" target="16">
      <data key="d0">0.590811</data>
    </edge>
    <edge source="7" target="17">
      <data key="d0">0.435055</data>
    </edge>
    <edge source="7" target="18">
      <data key="d0">0.495927</data>
    </edge>
    <edge source="7" target="21">
      <data key="d0">0.380261</data>
    </edge>
    <edge source="7" target="25">
      <data key="d0">0.551773</data>
    </edge>
    <edge source="7" target="26">
      <data key="d0">0.588103</data>
    </edge>
    <edge source="7" target="27">
      <data key="d0">0.520728</data>
    </edge>
    <edge source="7" target="28">
      <data key="d0">0.402372</data>
    </edge>
    <edge source="7" target="29">
      <data key="d0">0.380246</data>
    </edge>
    <edge source="7" target="30">
      <data key="d0">0.286228</data>
    </edge>
    <edge source="7" target="32">
      <data key="d0">0.534593</data>
    </edge>
    <edge source="7" target="33">
      <data key="d0">0.552091</data>
    </edge>
    <edge source="7" target="34">
      <data key="d0">0.425734</data>
    </edge>
    <edge source="7" target="35">
      <data key="d0">0.253347</data>
    </edge>
    <edge source="7" target="36">
      <data key="d0">0.452673</data>
    </edge>
    <edge source="7" target="39">
      <data key="d0">0.534575</data>
    </edge>
    <edge source="7" target="40">
      <data key="d0">0.305193</data>
    </edge>
    <edge source="7" target="43">
      <data key="d0">0.536348</data>
    </edge>
    <edge source="7" target="45">
      <data key="d0">0.585086</data>
    </edge>
    <edge source="7" target="47">
      <data key="d0">0.584693</data>
    </edge>
    <edge source="7" target="48">
      <data key="d0">0.381715</data>
    </edge>
    <edge source="7" target="49">
      <data key="d0">0.562992</data>
    </edge>
    <edge source="7" target="50">
      <data key="d0">0.584896</data>
    </edge>
    <edge source="7" target="51">
      <data key="d0">0.395284</data>
    </edge>
    <edge source="7" target="53">
      <data key="d0">0.582732</data>
    </edge>
    <edge source="7" target="54">
      <data key="d0">0.563413</data>
    </edge>
    <edge source="7" target="56">
      <data key="d0">0.540158</data>
    </edge>
    <edge source="7" target="59">
      <data key="d0">0.38093</data>
    </edge>
    <edge source="7" target="60">
      <data key="d0">-0.00652822</data>
    </edge>
    <edge source="7" target="61">
      <data key="d0">0.545903</data>
    </edge>
    <edge source="7" target="62">
      <data key="d0">0.444349</data>
    </edge>
    <edge source="7" target="65">
      <data key="d0">0.549393</data>
    </edge>
    <edge source="7" target="68">
      <data key="d0">0.566392</data>
    </edge>
    <edge source="7" target="72">
      <data key="d0">0.547143</data>
    </edge>
    <edge source="7" target="73">
      <data key="d0">0.105614</data>
    </edge>
    <edge source="7" target="74">
      <data key="d0">0.454449</data>
    </edge>
    <edge source="7" target="75">
      <data key="d0">0.578605</data>
    </edge>
    <edge source="7" target="77">
      <data key="d0">0.393871</data>
    </edge>
    <edge source="7" target="78">
      <data key="d0">0.175918</data>
    </edge>
    <edge source="7" target="79">
      <data key="d0">0.426816</data>
    </edge>
    <edge source="7" target="80">
      <data key="d0">0.594508</data>
    </edge>
    <edge source="7" target="83">
      <data key="d0">0.184129</data>
    </edge>
    <edge source="8" target="18">
      <data key="d0">0.57301</data>
    </edge>
    <edge source="8" target="24">
      <data key="d0">0.560569</data>
    </edge>
    <edge source="8" target="29">
      <data key="d0">0.570793</data>
    </edge>
    <edge source="8" target="30">
      <data key="d0">0.535355</data>
    </edge>
    <edge source="8" target="34">
      <data key="d0">0.454406</data>
    </edge>
    <edge source="8" target="35">
      <data key="d0">0.201384</data>
    </edge>
    <edge source="8" target="36">
      <data key="d0">0.371457</data>
    </edge>
    <edge source="8" target="40">
      <data key="d0">0.291666</data>
    </edge>
    <edge source="8" target="48">
      <data key="d0">0.550193</data>
    </edge>
    <edge source="8" target="51">
      <data key="d0">0.580542</data>
    </edge>
    <edge source="8" target="59">
      <data key="d0">0.579367</data>
    </edge>
    <edge source="8" target="60">
      <data key="d0">0.506466</data>
    </edge>
    <edge source="8" target="61">
      <data key="d0">0.550751</data>
    </edge>
    <edge source="8" target="72">
      <data key="d0">0.53196</data>
    </edge>
    <edge source="8" target="73">
      <data key="d0">0.13035</data>
    </edge>
    <edge source="8" target="77">
      <data key="d0">0.566113</data>
    </edge>
    <edge source="8" target="78">
      <data key="d0">0.445082</data>
    </edge>
    <edge source="8" target="79">
      <data key="d0">0.579618</data>
    </edge>
    <edge source="8" target="80">
      <data key="d0">0.585243</data>
    </edge>
    <edge source="8" target="83">
      <data key="d0">0.30686</data>
    </edge>
    <edge source="8" target="84">
      <data key="d0">0.518433</data>
    </edge>
    <edge source="9" target="18">
      <data key="d0">0.50542</data>
    </edge>
    <edge source="9" target="24">
      <data key="d0">0.566298</data>
    </edge>
    <edge source="9" target="30">
      <data key="d0">0.544618</data>
    </edge>
    <edge source="9" target="31">
      <data key="d0">0.451519</data>
    </edge>
    <edge source="9" target="34">
      <data key="d0">0.578797</data>
    </edge>
    <edge source="9" target="35">
      <data key="d0">0.161254</data>
    </edge>
    <edge source="9" target="36">
      <data key="d0">0.53845</data>
    </edge>
    <edge source="9" target="40">
      <data key="d0">0.471347</data>
    </edge>
    <edge source="9" target="48">
      <data key="d0">0.431685</data>
    </edge>
    <edge source="9" target="49">
      <data key="d0">0.591221</data>
    </edge>
    <edge source="9" target="59">
      <data key="d0">0.522109</data>
    </edge>
    <edge source="9" target="60">
      <data key="d0">0.345366</data>
    </edge>
    <edge source="9" target="61">
      <data key="d0">0.555787</data>
    </edge>
    <edge source="9" target="62">
      <data key="d0">0.569812</data>
    </edge>
    <edge source="9" target="65">
      <data key="d0">0.55277</data>
    </edge>
    <edge source="9" target="68">
      <data key="d0">0.578817</data>
    </edge>
    <edge source="9" target="73">
      <data key="d0">0.380056</data>
    </edge>
    <edge source="9" target="74">
      <data key="d0">0.484309</data>
    </edge>
    <edge source="9" target="78">
      <data key="d0">0.404877</data>
    </edge>
    <edge source="9" target="79">
      <data key="d0">0.486841</data>
    </edge>
    <edge source="9" target="80">
      <data key="d0">0.424567</data>
    </edge>
    <edge source="9" target="83">
      <data key="d0">0.432608</data>
    </edge>
    <edge source="10" target="28">
      <data key="d0">0.579996</data>
    </edge>
    <edge source="10" target="30">
      <data key="d0">0.483069</data>
    </edge>
    <edge source="10" target="34">
      <data key="d0">0.556928</data>
    </edge>
    <edge source="10" target="35">
      <data key="d0">0.345043</data>
    </edge>
    <edge source="10" target="36">
      <data key="d0">0.540598</data>
    </edge>
    <edge source="10" target="40">
      <data key="d0">0.450033</data>
    </edge>
    <edge source="10" target="48">
      <data key="d0">0.542316</data>
    </edge>
    <edge source="10" target="59">
      <data key="d0">0.405365</data>
    </edge>
    <edge source="10" target="60">
      <data key="d0">0.328485</data>
    </edge>
    <edge source="10" target="73">
      <data key="d0">0.460167</data>
    </edge>
    <edge source="10" target="78">
      <data key="d0">0.270046</data>
    </edge>
    <edge source="10" target="79">
      <data key="d0">0.500116</data>
    </edge>
    <edge source="10" target="83">
      <data key="d0">0.459866</data>
    </edge>
    <edge source="11" target="28">
      <data key="d0">0.580709</data>
    </edge>
    <edge source="11" target="29">
      <data key="d0">0.529504</data>
    </edge>
    <edge source="11" target="34">
      <data key="d0">0.527161</data>
    </edge>
    <edge source="11" target="35">
      <data key="d0">0.438895</data>
    </edge>
    <edge source="11" target="36">
      <data key="d0">0.355351</data>
    </edge>
    <edge source="11" target="40">
      <data key="d0">0.293646</data>
    </edge>
    <edge source="11" target="41">
      <data key="d0">0.570915</data>
    </edge>
    <edge source="11" target="46">
      <data key="d0">0.571389</data>
    </edge>
    <edge source="11" target="59">
      <data key="d0">0.506878</data>
    </edge>
    <edge source="11" target="60">
      <data key="d0">0.405918</data>
    </edge>
    <edge source="11" target="68">
      <data key="d0">0.555639</data>
    </edge>
    <edge source="11" target="72">
      <data key="d0">0.530903</data>
    </edge>
    <edge source="11" target="73">
      <data key="d0">0.327311</data>
    </edge>
    <edge source="11" target="78">
      <data key="d0">0.293273</data>
    </edge>
    <edge source="11" target="80">
      <data key="d0">0.566127</data>
    </edge>
    <edge source="11" target="83">
      <data key="d0">0.465007</data>
    </edge>
    <edge source="11" target="84">
      <data key="d0">0.534059</data>
    </edge>
    <edge source="12" target="34">
      <data key="d0">0.594056</data>
    </edge>
    <edge source="12" target="35">
      <data key="d0">0.465091</data>
    </edge>
    <edge source="12" target="36">
      <data key="d0">0.470688</data>
    </edge>
    <edge source="12" target="40">
      <data key="d0">0.344389</data>
    </edge>
    <edge source="12" target="48">
      <data key="d0">0.570101</data>
    </edge>
    <edge source="12" target="59">
      <data key="d0">0.4956</data>
    </edge>
    <edge source="12" target="60">
      <data key="d0">0.33564</data>
    </edge>
    <edge source="12" target="73">
      <data key="d0">0.324257</data>
    </edge>
    <edge source="12" target="78">
      <data key="d0">0.319235</data>
    </edge>
    <edge source="12" target="83">
      <data key="d0">0.474066</data>
    </edge>
    <edge source="13" target="30">
      <data key="d0">0.551011</data>
    </edge>
    <edge source="13" target="34">
      <data key="d0">0.549978</data>
    </edge>
    <edge source="13" target="35">
      <data key="d0">0.289577</data>
    </edge>
    <edge source="13" target="36">
      <data key="d0">0.542707</data>
    </edge>
    <edge source="13" target="40">
      <data key="d0">0.474951</data>
    </edge>
    <edge source="13" target="59">
      <data key="d0">0.487768</data>
    </edge>
    <edge source="13" target="60">
      <data key="d0">0.348426</data>
    </edge>
    <edge source="13" target="73">
      <data key="d0">0.366044</data>
    </edge>
    <edge source="13" target="78">
      <data key="d0">0.318117</data>
    </edge>
    <edge source="13" target="83">
      <data key="d0">0.456537</data>
    </edge>
    <edge source="14" target="18">
      <data key="d0">0.564889</data>
    </edge>
    <edge source="14" target="30">
      <data key="d0">0.549761</data>
    </edge>
    <edge source="14" target="31">
      <data key="d0">0.470486</data>
    </edge>
    <edge source="14" target="35">
      <data key="d0">0.362887</data>
    </edge>
    <edge source="14" target="36">
      <data key="d0">0.42575</data>
    </edge>
    <edge source="14" target="37">
      <data key="d0">0.566603</data>
    </edge>
    <edge source="14" target="40">
      <data key="d0">0.427336</data>
    </edge>
    <edge source="14" target="48">
      <data key="d0">0.372991</data>
    </edge>
    <edge source="14" target="49">
      <data key="d0">0.473639</data>
    </edge>
    <edge source="14" target="59">
      <data key="d0">0.436973</data>
    </edge>
    <edge source="14" target="60">
      <data key="d0">0.389405</data>
    </edge>
    <edge source="14" target="61">
      <data key="d0">0.594566</data>
    </edge>
    <edge source="14" target="73">
      <data key="d0">0.307318</data>
    </edge>
    <edge source="14" target="74">
      <data key="d0">0.591382</data>
    </edge>
    <edge source="14" target="78">
      <data key="d0">0.467929</data>
    </edge>
    <edge source="14" target="79">
      <data key="d0">0.557281</data>
    </edge>
    <edge source="14" target="83">
      <data key="d0">0.418795</data>
    </edge>
    <edge source="15" target="35">
      <data key="d0">0.36295</data>
    </edge>
    <edge source="15" target="36">
      <data key="d0">0.563445</data>
    </edge>
    <edge source="15" target="40">
      <data key="d0">0.467435</data>
    </edge>
    <edge source="15" target="48">
      <data key="d0">0.593155</data>
    </edge>
    <edge source="15" target="59">
      <data key="d0">0.501006</data>
    </edge>
    <edge source="15" target="60">
      <data key="d0">0.346277</data>
    </edge>
    <edge source="15" target="73">
      <data key="d0">0.307598</data>
    </edge>
    <edge source="15" target="78">
      <data key="d0">0.368793</data>
    </edge>
    <edge source="15" target="83">
      <data key="d0">0.573206</data>
    </edge>
    <edge source="16" target="18">
      <data key="d0">0.576356</data>
    </edge>
    <edge source="16" target="30">
      <data key="d0">0.491552</data>
    </edge>
    <edge source="16" target="34">
      <data key="d0">0.551975</data>
    </edge>
    <edge source="16" target="35">
      <data key="d0">0.338128</data>
    </edge>
    <edge source="16" target="36">
      <data key="d0">0.444723</data>
    </edge>
    <edge source="16" target="40">
      <data key="d0">0.46481</data>
    </edge>
    <edge source="16" target="48">
      <data key="d0">0.535702</data>
    </edge>
    <edge source="16" target="59">
      <data key="d0">0.478223</data>
    </edge>
    <edge source="16" target="60">
      <data key="d0">0.27933</data>
    </edge>
    <edge source="16" target="73">
      <data key="d0">0.23022</data>
    </edge>
    <edge source="16" target="78">
      <data key="d0">0.33124</data>
    </edge>
    <edge source="16" target="80">
      <data key="d0">0.554355</data>
    </edge>
    <edge source="16" target="83">
      <data key="d0">0.409062</data>
    </edge>
    <edge source="17" target="25">
      <data key="d0">0.55469</data>
    </edge>
    <edge source="17" target="28">
      <data key="d0">0.468196</data>
    </edge>
    <edge source="17" target="34">
      <data key="d0">0.540914</data>
    </edge>
    <edge source="17" target="35">
      <data key="d0">0.369613</data>
    </edge>
    <edge source="17" target="36">
      <data key="d0">0.430033</data>
    </edge>
    <edge source="17" target="37">
      <data key="d0">0.533352</data>
    </edge>
    <edge source="17" target="40">
      <data key="d0">0.439403</data>
    </edge>
    <edge source="17" target="41">
      <data key="d0">0.521053</data>
    </edge>
    <edge source="17" target="48">
      <data key="d0">0.41495</data>
    </edge>
    <edge source="17" target="49">
      <data key="d0">0.537691</data>
    </edge>
    <edge source="17" target="56">
      <data key="d0">0.562195</data>
    </edge>
    <edge source="17" target="59">
      <data key="d0">0.578918</data>
    </edge>
    <edge source="17" target="60">
      <data key="d0">0.424042</data>
    </edge>
    <edge source="17" target="65">
      <data key="d0">0.549166</data>
    </edge>
    <edge source="17" target="72">
      <data key="d0">0.488131</data>
    </edge>
    <edge source="17" target="73">
      <data key="d0">0.321683</data>
    </edge>
    <edge source="17" target="78">
      <data key="d0">0.432977</data>
    </edge>
    <edge source="17" target="79">
      <data key="d0">0.552772</data>
    </edge>
    <edge source="17" target="83">
      <data key="d0">0.493779</data>
    </edge>
    <edge source="17" target="84">
      <data key="d0">0.573882</data>
    </edge>
    <edge source="18" target="21">
      <data key="d0">0.567086</data>
    </edge>
    <edge source="18" target="22">
      <data key="d0">0.549002</data>
    </edge>
    <edge source="18" target="24">
      <data key="d0">0.577877</data>
    </edge>
    <edge source="18" target="25">
      <data key="d0">0.529626</data>
    </edge>
    <edge source="18" target="28">
      <data key="d0">0.409329</data>
    </edge>
    <edge source="18" target="30">
      <data key="d0">0.450341</data>
    </edge>
    <edge source="18" target="34">
      <data key="d0">0.550353</data>
    </edge>
    <edge source="18" target="35">
      <data key="d0">0.481481</data>
    </edge>
    <edge source="18" target="36">
      <data key="d0">0.510534</data>
    </edge>
    <edge source="18" target="40">
      <data key="d0">0.128161</data>
    </edge>
    <edge source="18" target="41">
      <data key="d0">0.460527</data>
    </edge>
    <edge source="18" target="46">
      <data key="d0">0.50973</data>
    </edge>
    <edge source="18" target="48">
      <data key="d0">0.561246</data>
    </edge>
    <edge source="18" target="51">
      <data key="d0">0.573249</data>
    </edge>
    <edge source="18" target="59">
      <data key="d0">0.358626</data>
    </edge>
    <edge source="18" target="60">
      <data key="d0">0.325461</data>
    </edge>
    <edge source="18" target="68">
      <data key="d0">0.542645</data>
    </edge>
    <edge source="18" target="72">
      <data key="d0">0.48403</data>
    </edge>
    <edge source="18" target="73">
      <data key="d0">0.517441</data>
    </edge>
    <edge source="18" target="74">
      <data key="d0">0.573429</data>
    </edge>
    <edge source="18" target="78">
      <data key="d0">0.349514</data>
    </edge>
    <edge source="18" target="79">
      <data key="d0">0.491313</data>
    </edge>
    <edge source="18" target="83">
      <data key="d0">0.530528</data>
    </edge>
    <edge source="18" target="84">
      <data key="d0">0.498835</data>
    </edge>
    <edge source="19" target="35">
      <data key="d0">0.40729</data>
    </edge>
    <edge source="19" target="40">
      <data key="d0">0.467007</data>
    </edge>
    <edge source="19" target="48">
      <data key="d0">0.462446</data>
    </edge>
    <edge source="19" target="59">
      <data key="d0">0.51902</data>
    </edge>
    <edge source="19" target="60">
      <data key="d0">0.302965</data>
    </edge>
    <edge source="19" target="73">
      <data key="d0">0.268873</data>
    </edge>
    <edge source="19" target="78">
      <data key="d0">0.314794</data>
    </edge>
    <edge source="19" target="83">
      <data key="d0">0.499139</data>
    </edge>
    <edge source="20" target="35">
      <data key="d0">0.369958</data>
    </edge>
    <edge source="20" target="36">
      <data key="d0">0.588407</data>
    </edge>
    <edge source="20" target="40">
      <data key="d0">0.409003</data>
    </edge>
    <edge source="20" target="48">
      <data key="d0">0.580505</data>
    </edge>
    <edge source="20" target="59">
      <data key="d0">0.496356</data>
    </edge>
    <edge source="20" target="60">
      <data key="d0">0.422112</data>
    </edge>
    <edge source="20" target="73">
      <data key="d0">0.338668</data>
    </edge>
    <edge source="20" target="78">
      <data key="d0">0.324538</data>
    </edge>
    <edge source="20" target="83">
      <data key="d0">0.454343</data>
    </edge>
    <edge source="21" target="24">
      <data key="d0">0.583753</data>
    </edge>
    <edge source="21" target="25">
      <data key="d0">0.472357</data>
    </edge>
    <edge source="21" target="28">
      <data key="d0">0.37306</data>
    </edge>
    <edge source="21" target="29">
      <data key="d0">0.556693</data>
    </edge>
    <edge source="21" target="30">
      <data key="d0">0.393184</data>
    </edge>
    <edge source="21" target="33">
      <data key="d0">0.533989</data>
    </edge>
    <edge source="21" target="34">
      <data key="d0">0.419227</data>
    </edge>
    <edge source="21" target="35">
      <data key="d0">0.395024</data>
    </edge>
    <edge source="21" target="36">
      <data key="d0">0.403928</data>
    </edge>
    <edge source="21" target="40">
      <data key="d0">0.23848</data>
    </edge>
    <edge source="21" target="46">
      <data key="d0">0.553497</data>
    </edge>
    <edge source="21" target="48">
      <data key="d0">0.492737</data>
    </edge>
    <edge source="21" target="49">
      <data key="d0">0.5295</data>
    </edge>
    <edge source="21" target="55">
      <data key="d0">0.579088</data>
    </edge>
    <edge source="21" target="56">
      <data key="d0">0.543948</data>
    </edge>
    <edge source="21" target="59">
      <data key="d0">0.503996</data>
    </edge>
    <edge source="21" target="60">
      <data key="d0">0.332985</data>
    </edge>
    <edge source="21" target="61">
      <data key="d0">0.52714</data>
    </edge>
    <edge source="21" target="62">
      <data key="d0">0.501516</data>
    </edge>
    <edge source="21" target="65">
      <data key="d0">0.582181</data>
    </edge>
    <edge source="21" target="66">
      <data key="d0">0.523708</data>
    </edge>
    <edge source="21" target="68">
      <data key="d0">0.46497</data>
    </edge>
    <edge source="21" target="69">
      <data key="d0">0.579332</data>
    </edge>
    <edge source="21" target="72">
      <data key="d0">0.364764</data>
    </edge>
    <edge source="21" target="73">
      <data key="d0">0.278803</data>
    </edge>
    <edge source="21" target="74">
      <data key="d0">0.59226</data>
    </edge>
    <edge source="21" target="77">
      <data key="d0">0.510221</data>
    </edge>
    <edge source="21" target="78">
      <data key="d0">0.397988</data>
    </edge>
    <edge source="21" target="80">
      <data key="d0">0.373154</data>
    </edge>
    <edge source="21" target="83">
      <data key="d0">0.29494</data>
    </edge>
    <edge source="21" target="84">
      <data key="d0">0.564499</data>
    </edge>
    <edge source="22" target="29">
      <data key="d0">0.542054</data>
    </edge>
    <edge source="22" target="30">
      <data key="d0">0.550539</data>
    </edge>
    <edge source="22" target="34">
      <data key="d0">0.523817</data>
    </edge>
    <edge source="22" target="35">
      <data key="d0">0.391236</data>
    </edge>
    <edge source="22" target="36">
      <data key="d0">0.344182</data>
    </edge>
    <edge source="22" target="40">
      <data key="d0">0.470175</data>
    </edge>
    <edge source="22" target="48">
      <data key="d0">0.493858</data>
    </edge>
    <edge source="22" target="59">
      <data key="d0">0.460911</data>
    </edge>
    <edge source="22" target="60">
      <data key="d0">0.202945</data>
    </edge>
    <edge source="22" target="73">
      <data key="d0">0.211918</data>
    </edge>
    <edge source="22" target="77">
      <data key="d0">0.570116</data>
    </edge>
    <edge source="22" target="78">
      <data key="d0">0.265529</data>
    </edge>
    <edge source="22" target="83">
      <data key="d0">0.526308</data>
    </edge>
    <edge source="23" target="35">
      <data key="d0">0.385618</data>
    </edge>
    <edge source="23" target="36">
      <data key="d0">0.585853</data>
    </edge>
    <edge source="23" target="40">
      <data key="d0">0.464877</data>
    </edge>
    <edge source="23" target="48">
      <data key="d0">0.556104</data>
    </edge>
    <edge source="23" target="59">
      <data key="d0">0.55071</data>
    </edge>
    <edge source="23" target="60">
      <data key="d0">0.325596</data>
    </edge>
    <edge source="23" target="73">
      <data key="d0">0.290657</data>
    </edge>
    <edge source="23" target="78">
      <data key="d0">0.342039</data>
    </edge>
    <edge source="23" target="83">
      <data key="d0">0.505864</data>
    </edge>
    <edge source="24" target="28">
      <data key="d0">0.476082</data>
    </edge>
    <edge source="24" target="29">
      <data key="d0">0.569406</data>
    </edge>
    <edge source="24" target="30">
      <data key="d0">0.472468</data>
    </edge>
    <edge source="24" target="34">
      <data key="d0">0.46152</data>
    </edge>
    <edge source="24" target="35">
      <data key="d0">0.530544</data>
    </edge>
    <edge source="24" target="36">
      <data key="d0">0.318841</data>
    </edge>
    <edge source="24" target="40">
      <data key="d0">0.377267</data>
    </edge>
    <edge source="24" target="48">
      <data key="d0">0.401479</data>
    </edge>
    <edge source="24" target="59">
      <data key="d0">0.457185</data>
    </edge>
    <edge source="24" target="60">
      <data key="d0">0.149615</data>
    </edge>
    <edge source="24" target="62">
      <data key="d0">0.554143</data>
    </edge>
    <edge source="24" target="72">
      <data key="d0">0.540429</data>
    </edge>
    <edge source="24" target="73">
      <data key="d0">0.164307</data>
    </edge>
    <edge source="24" target="77">
      <data key="d0">0.52774</data>
    </edge>
    <edge source="24" target="78">
      <data key="d0">0.178347</data>
    </edge>
    <edge source="24" target="79">
      <data key="d0">0.534329</data>
    </edge>
    <edge source="24" target="83">
      <data key="d0">0.396152</data>
    </edge>
    <edge source="25" target="29">
      <data key="d0">0.566401</data>
    </edge>
    <edge source="25" target="31">
      <data key="d0">0.533592</data>
    </edge>
    <edge source="25" target="34">
      <data key="d0">0.561208</data>
    </edge>
    <edge source="25" target="35">
      <data key="d0">0.279979</data>
    </edge>
    <edge source="25" target="36">
      <data key="d0">0.432791</data>
    </edge>
    <edge source="25" target="40">
      <data key="d0">0.366573</data>
    </edge>
    <edge source="25" target="48">
      <data key="d0">0.475918</data>
    </edge>
    <edge source="25" target="59">
      <data key="d0">0.457296</data>
    </edge>
    <edge source="25" target="60">
      <data key="d0">0.230106</data>
    </edge>
    <edge source="25" target="65">
      <data key="d0">0.549272</data>
    </edge>
    <edge source="25" target="72">
      <data key="d0">0.572365</data>
    </edge>
    <edge source="25" target="73">
      <data key="d0">0.189987</data>
    </edge>
    <edge source="25" target="74">
      <data key="d0">0.547797</data>
    </edge>
    <edge source="25" target="78">
      <data key="d0">0.223049</data>
    </edge>
    <edge source="25" target="79">
      <data key="d0">0.515127</data>
    </edge>
    <edge source="25" target="80">
      <data key="d0">0.53857</data>
    </edge>
    <edge source="25" target="83">
      <data key="d0">0.388463</data>
    </edge>
    <edge source="26" target="35">
      <data key="d0">0.44678</data>
    </edge>
    <edge source="26" target="36">
      <data key="d0">0.562045</data>
    </edge>
    <edge source="26" target="40">
      <data key="d0">0.384539</data>
    </edge>
    <edge source="26" target="48">
      <data key="d0">0.543043</data>
    </edge>
    <edge source="26" target="59">
      <data key="d0">0.422492</data>
    </edge>
    <edge source="26" target="60">
      <data key="d0">0.330521</data>
    </edge>
    <edge source="26" target="73">
      <data key="d0">0.262554</data>
    </edge>
    <edge source="26" target="78">
      <data key="d0">0.383602</data>
    </edge>
    <edge source="26" target="83">
      <data key="d0">0.590186</data>
    </edge>
    <edge source="27" target="28">
      <data key="d0">0.565721</data>
    </edge>
    <edge source="27" target="30">
      <data key="d0">0.558897</data>
    </edge>
    <edge source="27" target="34">
      <data key="d0">0.576897</data>
    </edge>
    <edge source="27" target="35">
      <data key="d0">0.344461</data>
    </edge>
    <edge source="27" target="36">
      <data key="d0">0.495649</data>
    </edge>
    <edge source="27" target="40">
      <data key="d0">0.4798</data>
    </edge>
    <edge source="27" target="48">
      <data key="d0">0.502083</data>
    </edge>
    <edge source="27" target="59">
      <data key="d0">0.505359</data>
    </edge>
    <edge source="27" target="60">
      <data key="d0">0.345472</data>
    </edge>
    <edge source="27" target="73">
      <data key="d0">0.307787</data>
    </edge>
    <edge source="27" target="78">
      <data key="d0">0.330152</data>
    </edge>
    <edge source="27" target="83">
      <data key="d0">0.434902</data>
    </edge>
    <edge source="28" target="29">
      <data key="d0">0.448338</data>
    </edge>
    <edge source="28" target="30">
      <data key="d0">0.510734</data>
    </edge>
    <edge source="28" target="31">
      <data key="d0">0.423077</data>
    </edge>
    <edge source="28" target="33">
      <data key="d0">0.552196</data>
    </edge>
    <edge source="28" target="35">
      <data key="d0">0.2175</data>
    </edge>
    <edge source="28" target="36">
      <data key="d0">0.42218</data>
    </edge>
    <edge source="28" target="37">
      <data key="d0">0.537194</data>
    </edge>
    <edge source="28" target="40">
      <data key="d0">0.381973</data>
    </edge>
    <edge source="28" target="41">
      <data key="d0">0.594314</data>
    </edge>
    <edge source="28" target="45">
      <data key="d0">0.516988</data>
    </edge>
    <edge source="28" target="46">
      <data key="d0">0.536599</data>
    </edge>
    <edge source="28" target="47">
      <data key="d0">0.545371</data>
    </edge>
    <edge source="28" target="48">
      <data key="d0">0.395744</data>
    </edge>
    <edge source="28" target="49">
      <data key="d0">0.369416</data>
    </edge>
    <edge source="28" target="50">
      <data key="d0">0.590902</data>
    </edge>
    <edge source="28" target="51">
      <data key="d0">0.528436</data>
    </edge>
    <edge source="28" target="53">
      <data key="d0">0.537545</data>
    </edge>
    <edge source="28" target="54">
      <data key="d0">0.517324</data>
    </edge>
    <edge source="28" target="59">
      <data key="d0">0.319329</data>
    </edge>
    <edge source="28" target="60">
      <data key="d0">0.330981</data>
    </edge>
    <edge source="28" target="61">
      <data key="d0">0.539685</data>
    </edge>
    <edge source="28" target="62">
      <data key="d0">0.548023</data>
    </edge>
    <edge source="28" target="65">
      <data key="d0">0.564559</data>
    </edge>
    <edge source="28" target="66">
      <data key="d0">0.580019</data>
    </edge>
    <edge source="28" target="73">
      <data key="d0">0.188975</data>
    </edge>
    <edge source="28" target="74">
      <data key="d0">0.525329</data>
    </edge>
    <edge source="28" target="75">
      <data key="d0">0.511903</data>
    </edge>
    <edge source="28" target="78">
      <data key="d0">0.518783</data>
    </edge>
    <edge source="28" target="79">
      <data key="d0">0.499472</data>
    </edge>
    <edge source="28" target="80">
      <data key="d0">0.414588</data>
    </edge>
    <edge source="28" target="83">
      <data key="d0">0.543018</data>
    </edge>
    <edge source="29" target="30">
      <data key="d0">0.386116</data>
    </edge>
    <edge source="29" target="31">
      <data key="d0">0.539026</data>
    </edge>
    <edge source="29" target="34">
      <data key="d0">0.290878</data>
    </edge>
    <edge source="29" target="35">
      <data key="d0">0.253271</data>
    </edge>
    <edge source="29" target="36">
      <data key="d0">0.461579</data>
    </edge>
    <edge source="29" target="40">
      <data key="d0">0.242922</data>
    </edge>
    <edge source="29" target="41">
      <data key="d0">0.509238</data>
    </edge>
    <edge source="29" target="47">
      <data key="d0">0.589861</data>
    </edge>
    <edge source="29" target="48">
      <data key="d0">0.409641</data>
    </edge>
    <edge source="29" target="49">
      <data key="d0">0.523135</data>
    </edge>
    <edge source="29" target="51">
      <data key="d0">0.486398</data>
    </edge>
    <edge source="29" target="56">
      <data key="d0">0.555493</data>
    </edge>
    <edge source="29" target="59">
      <data key="d0">0.260094</data>
    </edge>
    <edge source="29" target="60">
      <data key="d0">0.323725</data>
    </edge>
    <edge source="29" target="61">
      <data key="d0">0.421654</data>
    </edge>
    <edge source="29" target="65">
      <data key="d0">0.545774</data>
    </edge>
    <edge source="29" target="68">
      <data key="d0">0.552673</data>
    </edge>
    <edge source="29" target="72">
      <data key="d0">0.541539</data>
    </edge>
    <edge source="29" target="73">
      <data key="d0">0.403057</data>
    </edge>
    <edge source="29" target="74">
      <data key="d0">0.428649</data>
    </edge>
    <edge source="29" target="78">
      <data key="d0">0.308471</data>
    </edge>
    <edge source="29" target="79">
      <data key="d0">0.386382</data>
    </edge>
    <edge source="29" target="83">
      <data key="d0">0.260419</data>
    </edge>
    <edge source="29" target="84">
      <data key="d0">0.565062</data>
    </edge>
    <edge source="30" target="31">
      <data key="d0">0.31871</data>
    </edge>
    <edge source="30" target="33">
      <data key="d0">0.581774</data>
    </edge>
    <edge source="30" target="34">
      <data key="d0">0.59021</data>
    </edge>
    <edge source="30" target="35">
      <data key="d0">0.294181</data>
    </edge>
    <edge source="30" target="36">
      <data key="d0">0.356492</data>
    </edge>
    <edge source="30" target="37">
      <data key="d0">0.380933</data>
    </edge>
    <edge source="30" target="40">
      <data key="d0">0.414967</data>
    </edge>
    <edge source="30" target="41">
      <data key="d0">0.392309</data>
    </edge>
    <edge source="30" target="42">
      <data key="d0">0.573015</data>
    </edge>
    <edge source="30" target="45">
      <data key="d0">0.54678</data>
    </edge>
    <edge source="30" target="46">
      <data key="d0">0.459024</data>
    </edge>
    <edge source="30" target="47">
      <data key="d0">0.56544</data>
    </edge>
    <edge source="30" target="48">
      <data key="d0">0.233322</data>
    </edge>
    <edge source="30" target="49">
      <data key="d0">0.315093</data>
    </edge>
    <edge source="30" target="51">
      <data key="d0">0.489801</data>
    </edge>
    <edge source="30" target="56">
      <data key="d0">0.586364</data>
    </edge>
    <edge source="30" target="59">
      <data key="d0">0.384355</data>
    </edge>
    <edge source="30" target="60">
      <data key="d0">0.273884</data>
    </edge>
    <edge source="30" target="62">
      <data key="d0">0.426681</data>
    </edge>
    <edge source="30" target="64">
      <data key="d0">0.541191</data>
    </edge>
    <edge source="30" target="65">
      <data key="d0">0.320323</data>
    </edge>
    <edge source="30" target="68">
      <data key="d0">0.51243</data>
    </edge>
    <edge source="30" target="69">
      <data key="d0">0.488213</data>
    </edge>
    <edge source="30" target="72">
      <data key="d0">0.353673</data>
    </edge>
    <edge source="30" target="73">
      <data key="d0">0.192055</data>
    </edge>
    <edge source="30" target="74">
      <data key="d0">0.39301</data>
    </edge>
    <edge source="30" target="75">
      <data key="d0">0.480887</data>
    </edge>
    <edge source="30" target="76">
      <data key="d0">0.553679</data>
    </edge>
    <edge source="30" target="77">
      <data key="d0">0.54157</data>
    </edge>
    <edge source="30" target="78">
      <data key="d0">0.348269</data>
    </edge>
    <edge source="30" target="79">
      <data key="d0">0.349938</data>
    </edge>
    <edge source="30" target="80">
      <data key="d0">0.392639</data>
    </edge>
    <edge source="30" target="83">
      <data key="d0">0.514907</data>
    </edge>
    <edge source="30" target="84">
      <data key="d0">0.564857</data>
    </edge>
    <edge source="31" target="33">
      <data key="d0">0.588297</data>
    </edge>
    <edge source="31" target="34">
      <data key="d0">0.414058</data>
    </edge>
    <edge source="31" target="35">
      <data key="d0">0.438382</data>
    </edge>
    <edge source="31" target="36">
      <data key="d0">0.533374</data>
    </edge>
    <edge source="31" target="40">
      <data key="d0">0.159163</data>
    </edge>
    <edge source="31" target="41">
      <data key="d0">0.581312</data>
    </edge>
    <edge source="31" target="43">
      <data key="d0">0.583875</data>
    </edge>
    <edge source="31" target="48">
      <data key="d0">0.564374</data>
    </edge>
    <edge source="31" target="49">
      <data key="d0">0.578277</data>
    </edge>
    <edge source="31" target="51">
      <data key="d0">0.484878</data>
    </edge>
    <edge source="31" target="56">
      <data key="d0">0.517765</data>
    </edge>
    <edge source="31" target="59">
      <data key="d0">0.37614</data>
    </edge>
    <edge source="31" target="60">
      <data key="d0">0.191823</data>
    </edge>
    <edge source="31" target="61">
      <data key="d0">0.593356</data>
    </edge>
    <edge source="31" target="62">
      <data key="d0">0.523725</data>
    </edge>
    <edge source="31" target="68">
      <data key="d0">0.560896</data>
    </edge>
    <edge source="31" target="72">
      <data key="d0">0.470598</data>
    </edge>
    <edge source="31" target="73">
      <data key="d0">-0.0094591</data>
    </edge>
    <edge source="31" target="77">
      <data key="d0">0.445082</data>
    </edge>
    <edge source="31" target="78">
      <data key="d0">0.282965</data>
    </edge>
    <edge source="31" target="80">
      <data key="d0">0.554014</data>
    </edge>
    <edge source="31" target="83">
      <data key="d0">0.350162</data>
    </edge>
    <edge source="31" target="84">
      <data key="d0">0.506731</data>
    </edge>
    <edge source="32" target="34">
      <data key="d0">0.489903</data>
    </edge>
    <edge source="32" target="35">
      <data key="d0">0.426879</data>
    </edge>
    <edge source="32" target="36">
      <data key="d0">0.502645</data>
    </edge>
    <edge source="32" target="40">
      <data key="d0">0.382764</data>
    </edge>
    <edge source="32" target="48">
      <data key="d0">0.494413</data>
    </edge>
    <edge source="32" target="59">
      <data key="d0">0.55301</data>
    </edge>
    <edge source="32" target="60">
      <data key="d0">0.397433</data>
    </edge>
    <edge source="32" target="73">
      <data key="d0">0.266797</data>
    </edge>
    <edge source="32" target="78">
      <data key="d0">0.378808</data>
    </edge>
    <edge source="32" target="83">
      <data key="d0">0.478609</data>
    </edge>
    <edge source="33" target="34">
      <data key="d0">0.519138</data>
    </edge>
    <edge source="33" target="35">
      <data key="d0">0.358558</data>
    </edge>
    <edge source="33" target="36">
      <data key="d0">0.504301</data>
    </edge>
    <edge source="33" target="40">
      <data key="d0">0.41336</data>
    </edge>
    <edge source="33" target="48">
      <data key="d0">0.336388</data>
    </edge>
    <edge source="33" target="59">
      <data key="d0">0.513272</data>
    </edge>
    <edge source="33" target="60">
      <data key="d0">0.325373</data>
    </edge>
    <edge source="33" target="73">
      <data key="d0">0.344865</data>
    </edge>
    <edge source="33" target="78">
      <data key="d0">0.23358</data>
    </edge>
    <edge source="33" target="79">
      <data key="d0">0.529308</data>
    </edge>
    <edge source="33" target="83">
      <data key="d0">0.41624</data>
    </edge>
    <edge source="34" target="35">
      <data key="d0">0.401018</data>
    </edge>
    <edge source="34" target="36">
      <data key="d0">0.550902</data>
    </edge>
    <edge source="34" target="37">
      <data key="d0">0.376711</data>
    </edge>
    <edge source="34" target="39">
      <data key="d0">0.560079</data>
    </edge>
    <edge source="34" target="40">
      <data key="d0">0.3098</data>
    </edge>
    <edge source="34" target="42">
      <data key="d0">0.587294</data>
    </edge>
    <edge source="34" target="43">
      <data key="d0">0.57527</data>
    </edge>
    <edge source="34" target="45">
      <data key="d0">0.558826</data>
    </edge>
    <edge source="34" target="46">
      <data key="d0">0.461383</data>
    </edge>
    <edge source="34" target="48">
      <data key="d0">0.280197</data>
    </edge>
    <edge source="34" target="49">
      <data key="d0">0.341601</data>
    </edge>
    <edge source="34" target="52">
      <data key="d0">0.59124</data>
    </edge>
    <edge source="34" target="54">
      <data key="d0">0.580438</data>
    </edge>
    <edge source="34" target="55">
      <data key="d0">0.561675</data>
    </edge>
    <edge source="34" target="56">
      <data key="d0">0.551425</data>
    </edge>
    <edge source="34" target="59">
      <data key="d0">0.275165</data>
    </edge>
    <edge source="34" target="60">
      <data key="d0">0.220553</data>
    </edge>
    <edge source="34" target="62">
      <data key="d0">0.55251</data>
    </edge>
    <edge source="34" target="65">
      <data key="d0">0.520529</data>
    </edge>
    <edge source="34" target="66">
      <data key="d0">0.46682</data>
    </edge>
    <edge source="34" target="68">
      <data key="d0">0.562267</data>
    </edge>
    <edge source="34" target="69">
      <data key="d0">0.482855</data>
    </edge>
    <edge source="34" target="72">
      <data key="d0">0.496044</data>
    </edge>
    <edge source="34" target="73">
      <data key="d0">0.233372</data>
    </edge>
    <edge source="34" target="74">
      <data key="d0">0.525722</data>
    </edge>
    <edge source="34" target="75">
      <data key="d0">0.504785</data>
    </edge>
    <edge source="34" target="76">
      <data key="d0">0.594022</data>
    </edge>
    <edge source="34" target="77">
      <data key="d0">0.572895</data>
    </edge>
    <edge source="34" target="78">
      <data key="d0">0.45299</data>
    </edge>
    <edge source="34" target="79">
      <data key="d0">0.396911</data>
    </edge>
    <edge source="34" target="80">
      <data key="d0">0.518196</data>
    </edge>
    <edge source="35" target="36">
      <data key="d0">0.12964</data>
    </edge>
    <edge source="35" target="37">
      <data key="d0">0.176297</data>
    </edge>
    <edge source="35" target="38">
      <data key="d0">0.352013</data>
    </edge>
    <edge source="35" target="39">
      <data key="d0">0.351572</data>
    </edge>
    <edge source="35" target="41">
      <data key="d0">0.271725</data>
    </edge>
    <edge source="35" target="42">
      <data key="d0">0.280315</data>
    </edge>
    <edge source="35" target="43">
      <data key="d0">0.280171</data>
    </edge>
    <edge source="35" target="44">
      <data key="d0">0.356818</data>
    </edge>
    <edge source="35" target="45">
      <data key="d0">0.390075</data>
    </edge>
    <edge source="35" target="46">
      <data key="d0">0.317448</data>
    </edge>
    <edge source="35" target="47">
      <data key="d0">0.360978</data>
    </edge>
    <edge source="35" target="48">
      <data key="d0">0.152394</data>
    </edge>
    <edge source="35" target="49">
      <data key="d0">0.263282</data>
    </edge>
    <edge source="35" target="50">
      <data key="d0">0.306182</data>
    </edge>
    <edge source="35" target="51">
      <data key="d0">0.482984</data>
    </edge>
    <edge source="35" target="52">
      <data key="d0">0.34132</data>
    </edge>
    <edge source="35" target="53">
      <data key="d0">0.529335</data>
    </edge>
    <edge source="35" target="54">
      <data key="d0">0.447449</data>
    </edge>
    <edge source="35" target="55">
      <data key="d0">0.289059</data>
    </edge>
    <edge source="35" target="56">
      <data key="d0">0.318124</data>
    </edge>
    <edge source="35" target="57">
      <data key="d0">0.468135</data>
    </edge>
    <edge source="35" target="58">
      <data key="d0">0.308114</data>
    </edge>
    <edge source="35" target="59">
      <data key="d0">0.130513</data>
    </edge>
    <edge source="35" target="60">
      <data key="d0">0.142005</data>
    </edge>
    <edge source="35" target="61">
      <data key="d0">0.506839</data>
    </edge>
    <edge source="35" target="62">
      <data key="d0">0.396986</data>
    </edge>
    <edge source="35" target="63">
      <data key="d0">0.404</data>
    </edge>
    <edge source="35" target="64">
      <data key="d0">0.391696</data>
    </edge>
    <edge source="35" target="65">
      <data key="d0">0.403324</data>
    </edge>
    <edge source="35" target="66">
      <data key="d0">0.303014</data>
    </edge>
    <edge source="35" target="67">
      <data key="d0">0.396085</data>
    </edge>
    <edge source="35" target="68">
      <data key="d0">0.274391</data>
    </edge>
    <edge source="35" target="69">
      <data key="d0">0.275542</data>
    </edge>
    <edge source="35" target="70">
      <data key="d0">0.458285</data>
    </edge>
    <edge source="35" target="71">
      <data key="d0">0.424724</data>
    </edge>
    <edge source="35" target="72">
      <data key="d0">0.226003</data>
    </edge>
    <edge source="35" target="75">
      <data key="d0">0.488949</data>
    </edge>
    <edge source="35" target="76">
      <data key="d0">0.40847</data>
    </edge>
    <edge source="35" target="77">
      <data key="d0">0.38717</data>
    </edge>
    <edge source="35" target="78">
      <data key="d0">0.260792</data>
    </edge>
    <edge source="35" target="79">
      <data key="d0">0.38297</data>
    </edge>
    <edge source="35" target="80">
      <data key="d0">0.440128</data>
    </edge>
    <edge source="35" target="81">
      <data key="d0">0.416579</data>
    </edge>
    <edge source="35" target="82">
      <data key="d0">0.408228</data>
    </edge>
    <edge source="35" target="83">
      <data key="d0">0.45956</data>
    </edge>
    <edge source="35" target="84">
      <data key="d0">0.257672</data>
    </edge>
    <edge source="36" target="37">
      <data key="d0">0.423873</data>
    </edge>
    <edge source="36" target="38">
      <data key="d0">0.506719</data>
    </edge>
    <edge source="36" target="39">
      <data key="d0">0.540853</data>
    </edge>
    <edge source="36" target="40">
      <data key="d0">0.431099</data>
    </edge>
    <edge source="36" target="41">
      <data key="d0">0.511709</data>
    </edge>
    <edge source="36" target="42">
      <data key="d0">0.528131</data>
    </edge>
    <edge source="36" target="43">
      <data key="d0">0.568532</data>
    </edge>
    <edge source="36" target="46">
      <data key="d0">0.503938</data>
    </edge>
    <edge source="36" target="47">
      <data key="d0">0.572411</data>
    </edge>
    <edge source="36" target="48">
      <data key="d0">0.355666</data>
    </edge>
    <edge source="36" target="49">
      <data key="d0">0.379591</data>
    </edge>
    <edge source="36" target="50">
      <data key="d0">0.506745</data>
    </edge>
    <edge source="36" target="51">
      <data key="d0">0.385096</data>
    </edge>
    <edge source="36" target="52">
      <data key="d0">0.591367</data>
    </edge>
    <edge source="36" target="53">
      <data key="d0">0.455962</data>
    </edge>
    <edge source="36" target="54">
      <data key="d0">0.516397</data>
    </edge>
    <edge source="36" target="55">
      <data key="d0">0.520404</data>
    </edge>
    <edge source="36" target="56">
      <data key="d0">0.54131</data>
    </edge>
    <edge source="36" target="58">
      <data key="d0">0.555503</data>
    </edge>
    <edge source="36" target="59">
      <data key="d0">0.320448</data>
    </edge>
    <edge source="36" target="60">
      <data key="d0">0.107416</data>
    </edge>
    <edge source="36" target="61">
      <data key="d0">0.38211</data>
    </edge>
    <edge source="36" target="62">
      <data key="d0">0.534786</data>
    </edge>
    <edge source="36" target="65">
      <data key="d0">0.379009</data>
    </edge>
    <edge source="36" target="66">
      <data key="d0">0.538593</data>
    </edge>
    <edge source="36" target="67">
      <data key="d0">0.578826</data>
    </edge>
    <edge source="36" target="68">
      <data key="d0">0.503798</data>
    </edge>
    <edge source="36" target="69">
      <data key="d0">0.570459</data>
    </edge>
    <edge source="36" target="70">
      <data key="d0">0.589914</data>
    </edge>
    <edge source="36" target="71">
      <data key="d0">0.514265</data>
    </edge>
    <edge source="36" target="72">
      <data key="d0">0.555206</data>
    </edge>
    <edge source="36" target="73">
      <data key="d0">0.252714</data>
    </edge>
    <edge source="36" target="74">
      <data key="d0">0.251091</data>
    </edge>
    <edge source="36" target="75">
      <data key="d0">0.486757</data>
    </edge>
    <edge source="36" target="76">
      <data key="d0">0.564819</data>
    </edge>
    <edge source="36" target="77">
      <data key="d0">0.433522</data>
    </edge>
    <edge source="36" target="78">
      <data key="d0">0.282517</data>
    </edge>
    <edge source="36" target="79">
      <data key="d0">0.409194</data>
    </edge>
    <edge source="36" target="80">
      <data key="d0">0.334828</data>
    </edge>
    <edge source="36" target="81">
      <data key="d0">0.557234</data>
    </edge>
    <edge source="36" target="82">
      <data key="d0">0.569419</data>
    </edge>
    <edge source="36" target="83">
      <data key="d0">0.477033</data>
    </edge>
    <edge source="37" target="40">
      <data key="d0">0.319735</data>
    </edge>
    <edge source="37" target="51">
      <data key="d0">0.578658</data>
    </edge>
    <edge source="37" target="59">
      <data key="d0">0.473991</data>
    </edge>
    <edge source="37" target="60">
      <data key="d0">0.28513</data>
    </edge>
    <edge source="37" target="62">
      <data key="d0">0.537408</data>
    </edge>
    <edge source="37" target="65">
      <data key="d0">0.534705</data>
    </edge>
    <edge source="37" target="68">
      <data key="d0">0.526512</data>
    </edge>
    <edge source="37" target="72">
      <data key="d0">0.586971</data>
    </edge>
    <edge source="37" target="73">
      <data key="d0">0.416726</data>
    </edge>
    <edge source="37" target="74">
      <data key="d0">0.527687</data>
    </edge>
    <edge source="37" target="77">
      <data key="d0">0.503325</data>
    </edge>
    <edge source="37" target="78">
      <data key="d0">0.263456</data>
    </edge>
    <edge source="37" target="79">
      <data key="d0">0.541602</data>
    </edge>
    <edge source="37" target="80">
      <data key="d0">0.509531</data>
    </edge>
    <edge source="37" target="83">
      <data key="d0">0.337436</data>
    </edge>
    <edge source="38" target="40">
      <data key="d0">0.438115</data>
    </edge>
    <edge source="38" target="48">
      <data key="d0">0.566957</data>
    </edge>
    <edge source="38" target="59">
      <data key="d0">0.543572</data>
    </edge>
    <edge source="38" target="60">
      <data key="d0">0.33857</data>
    </edge>
    <edge source="38" target="73">
      <data key="d0">0.307379</data>
    </edge>
    <edge source="38" target="78">
      <data key="d0">0.314017</data>
    </edge>
    <edge source="38" target="83">
      <data key="d0">0.48376</data>
    </edge>
    <edge source="39" target="40">
      <data key="d0">0.392491</data>
    </edge>
    <edge source="39" target="48">
      <data key="d0">0.578885</data>
    </edge>
    <edge source="39" target="59">
      <data key="d0">0.534219</data>
    </edge>
    <edge source="39" target="60">
      <data key="d0">0.393769</data>
    </edge>
    <edge source="39" target="73">
      <data key="d0">0.447962</data>
    </edge>
    <edge source="39" target="78">
      <data key="d0">0.326353</data>
    </edge>
    <edge source="39" target="79">
      <data key="d0">0.568918</data>
    </edge>
    <edge source="39" target="83">
      <data key="d0">0.588145</data>
    </edge>
    <edge source="40" target="41">
      <data key="d0">0.441194</data>
    </edge>
    <edge source="40" target="42">
      <data key="d0">0.549119</data>
    </edge>
    <edge source="40" target="43">
      <data key="d0">0.526932</data>
    </edge>
    <edge source="40" target="44">
      <data key="d0">0.544036</data>
    </edge>
    <edge source="40" target="45">
      <data key="d0">0.411596</data>
    </edge>
    <edge source="40" target="46">
      <data key="d0">0.430708</data>
    </edge>
    <edge source="40" target="47">
      <data key="d0">0.379224</data>
    </edge>
    <edge source="40" target="48">
      <data key="d0">0.129346</data>
    </edge>
    <edge source="40" target="49">
      <data key="d0">0.165289</data>
    </edge>
    <edge source="40" target="50">
      <data key="d0">0.507783</data>
    </edge>
    <edge source="40" target="51">
      <data key="d0">0.34661</data>
    </edge>
    <edge source="40" target="52">
      <data key="d0">0.55055</data>
    </edge>
    <edge source="40" target="53">
      <data key="d0">0.317788</data>
    </edge>
    <edge source="40" target="54">
      <data key="d0">0.443353</data>
    </edge>
    <edge source="40" target="55">
      <data key="d0">0.494167</data>
    </edge>
    <edge source="40" target="56">
      <data key="d0">0.544702</data>
    </edge>
    <edge source="40" target="57">
      <data key="d0">0.441027</data>
    </edge>
    <edge source="40" target="58">
      <data key="d0">0.557784</data>
    </edge>
    <edge source="40" target="59">
      <data key="d0">0.494325</data>
    </edge>
    <edge source="40" target="60">
      <data key="d0">0.0644846</data>
    </edge>
    <edge source="40" target="61">
      <data key="d0">0.409236</data>
    </edge>
    <edge source="40" target="62">
      <data key="d0">0.459331</data>
    </edge>
    <edge source="40" target="63">
      <data key="d0">0.400326</data>
    </edge>
    <edge source="40" target="64">
      <data key="d0">0.379419</data>
    </edge>
    <edge source="40" target="65">
      <data key="d0">0.136559</data>
    </edge>
    <edge source="40" target="66">
      <data key="d0">0.499834</data>
    </edge>
    <edge source="40" target="67">
      <data key="d0">0.509997</data>
    </edge>
    <edge source="40" target="68">
      <data key="d0">0.501704</data>
    </edge>
    <edge source="40" target="69">
      <data key="d0">0.431714</data>
    </edge>
    <edge source="40" target="70">
      <data key="d0">0.361137</data>
    </edge>
    <edge source="40" target="71">
      <data key="d0">0.425024</data>
    </edge>
    <edge source="40" target="72">
      <data key="d0">0.49604</data>
    </edge>
    <edge source="40" target="73">
      <data key="d0">0.249464</data>
    </edge>
    <edge source="40" target="74">
      <data key="d0">0.191188</data>
    </edge>
    <edge source="40" target="75">
      <data key="d0">0.336345</data>
    </edge>
    <edge source="40" target="76">
      <data key="d0">0.449326</data>
    </edge>
    <edge source="40" target="77">
      <data key="d0">0.316681</data>
    </edge>
    <edge source="40" target="78">
      <data key="d0">0.184574</data>
    </edge>
    <edge source="40" target="79">
      <data key="d0">0.300671</data>
    </edge>
    <edge source="40" target="80">
      <data key="d0">0.236686</data>
    </edge>
    <edge source="40" target="81">
      <data key="d0">0.472376</data>
    </edge>
    <edge source="40" target="82">
      <data key="d0">0.456625</data>
    </edge>
    <edge source="40" target="83">
      <data key="d0">0.24909</data>
    </edge>
    <edge source="40" target="84">
      <data key="d0">0.523263</data>
    </edge>
    <edge source="41" target="48">
      <data key="d0">0.414205</data>
    </edge>
    <edge source="41" target="49">
      <data key="d0">0.553714</data>
    </edge>
    <edge source="41" target="59">
      <data key="d0">0.356231</data>
    </edge>
    <edge source="41" target="60">
      <data key="d0">0.133645</data>
    </edge>
    <edge source="41" target="73">
      <data key="d0">0.235461</data>
    </edge>
    <edge source="41" target="77">
      <data key="d0">0.516611</data>
    </edge>
    <edge source="41" target="78">
      <data key="d0">0.405721</data>
    </edge>
    <edge source="41" target="80">
      <data key="d0">0.526393</data>
    </edge>
    <edge source="41" target="83">
      <data key="d0">0.342518</data>
    </edge>
    <edge source="42" target="48">
      <data key="d0">0.546124</data>
    </edge>
    <edge source="42" target="59">
      <data key="d0">0.494452</data>
    </edge>
    <edge source="42" target="60">
      <data key="d0">0.278274</data>
    </edge>
    <edge source="42" target="73">
      <data key="d0">0.340692</data>
    </edge>
    <edge source="42" target="78">
      <data key="d0">0.287776</data>
    </edge>
    <edge source="42" target="83">
      <data key="d0">0.454739</data>
    </edge>
    <edge source="43" target="48">
      <data key="d0">0.531558</data>
    </edge>
    <edge source="43" target="59">
      <data key="d0">0.521055</data>
    </edge>
    <edge source="43" target="60">
      <data key="d0">0.335803</data>
    </edge>
    <edge source="43" target="73">
      <data key="d0">0.360412</data>
    </edge>
    <edge source="43" target="78">
      <data key="d0">0.331218</data>
    </edge>
    <edge source="43" target="79">
      <data key="d0">0.582342</data>
    </edge>
    <edge source="43" target="83">
      <data key="d0">0.508192</data>
    </edge>
    <edge source="44" target="48">
      <data key="d0">0.524408</data>
    </edge>
    <edge source="44" target="59">
      <data key="d0">0.533898</data>
    </edge>
    <edge source="44" target="60">
      <data key="d0">0.311279</data>
    </edge>
    <edge source="44" target="73">
      <data key="d0">0.316061</data>
    </edge>
    <edge source="44" target="78">
      <data key="d0">0.356464</data>
    </edge>
    <edge source="44" target="83">
      <data key="d0">0.539402</data>
    </edge>
    <edge source="45" target="48">
      <data key="d0">0.56316</data>
    </edge>
    <edge source="45" target="59">
      <data key="d0">0.510957</data>
    </edge>
    <edge source="45" target="60">
      <data key="d0">0.332295</data>
    </edge>
    <edge source="45" target="73">
      <data key="d0">0.235347</data>
    </edge>
    <edge source="45" target="78">
      <data key="d0">0.341628</data>
    </edge>
    <edge source="45" target="83">
      <data key="d0">0.513381</data>
    </edge>
    <edge source="46" target="48">
      <data key="d0">0.536285</data>
    </edge>
    <edge source="46" target="59">
      <data key="d0">0.442733</data>
    </edge>
    <edge source="46" target="60">
      <data key="d0">0.318588</data>
    </edge>
    <edge source="46" target="65">
      <data key="d0">0.560707</data>
    </edge>
    <edge source="46" target="73">
      <data key="d0">0.178416</data>
    </edge>
    <edge source="46" target="77">
      <data key="d0">0.542724</data>
    </edge>
    <edge source="46" target="78">
      <data key="d0">0.351334</data>
    </edge>
    <edge source="46" target="79">
      <data key="d0">0.563947</data>
    </edge>
    <edge source="46" target="83">
      <data key="d0">0.444055</data>
    </edge>
    <edge source="47" target="48">
      <data key="d0">0.532904</data>
    </edge>
    <edge source="47" target="59">
      <data key="d0">0.512155</data>
    </edge>
    <edge source="47" target="60">
      <data key="d0">0.378841</data>
    </edge>
    <edge source="47" target="72">
      <data key="d0">0.545884</data>
    </edge>
    <edge source="47" target="73">
      <data key="d0">0.265388</data>
    </edge>
    <edge source="47" target="78">
      <data key="d0">0.359877</data>
    </edge>
    <edge source="47" target="83">
      <data key="d0">0.540951</data>
    </edge>
    <edge source="48" target="50">
      <data key="d0">0.449669</data>
    </edge>
    <edge source="48" target="51">
      <data key="d0">0.402005</data>
    </edge>
    <edge source="48" target="52">
      <data key="d0">0.423731</data>
    </edge>
    <edge source="48" target="53">
      <data key="d0">0.495328</data>
    </edge>
    <edge source="48" target="54">
      <data key="d0">0.518781</data>
    </edge>
    <edge source="48" target="55">
      <data key="d0">0.533259</data>
    </edge>
    <edge source="48" target="56">
      <data key="d0">0.564023</data>
    </edge>
    <edge source="48" target="57">
      <data key="d0">0.496929</data>
    </edge>
    <edge source="48" target="58">
      <data key="d0">0.488125</data>
    </edge>
    <edge source="48" target="59">
      <data key="d0">0.287491</data>
    </edge>
    <edge source="48" target="60">
      <data key="d0">0.292357</data>
    </edge>
    <edge source="48" target="61">
      <data key="d0">0.503047</data>
    </edge>
    <edge source="48" target="62">
      <data key="d0">0.451956</data>
    </edge>
    <edge source="48" target="64">
      <data key="d0">0.582053</data>
    </edge>
    <edge source="48" target="65">
      <data key="d0">0.537097</data>
    </edge>
    <edge source="48" target="66">
      <data key="d0">0.490631</data>
    </edge>
    <edge source="48" target="67">
      <data key="d0">0.529976</data>
    </edge>
    <edge source="48" target="68">
      <data key="d0">0.419332</data>
    </edge>
    <edge source="48" target="69">
      <data key="d0">0.535136</data>
    </edge>
    <edge source="48" target="70">
      <data key="d0">0.593044</data>
    </edge>
    <edge source="48" target="71">
      <data key="d0">0.516933</data>
    </edge>
    <edge source="48" target="72">
      <data key="d0">0.372051</data>
    </edge>
    <edge source="48" target="73">
      <data key="d0">0.298721</data>
    </edge>
    <edge source="48" target="74">
      <data key="d0">0.490508</data>
    </edge>
    <edge source="48" target="76">
      <data key="d0">0.531402</data>
    </edge>
    <edge source="48" target="77">
      <data key="d0">0.362469</data>
    </edge>
    <edge source="48" target="78">
      <data key="d0">0.285315</data>
    </edge>
    <edge source="48" target="79">
      <data key="d0">0.48952</data>
    </edge>
    <edge source="48" target="80">
      <data key="d0">0.335171</data>
    </edge>
    <edge source="48" target="81">
      <data key="d0">0.457162</data>
    </edge>
    <edge source="48" target="82">
      <data key="d0">0.495171</data>
    </edge>
    <edge source="48" target="83">
      <data key="d0">0.350071</data>
    </edge>
    <edge source="48" target="84">
      <data key="d0">0.30798</data>
    </edge>
    <edge source="49" target="59">
      <data key="d0">0.488201</data>
    </edge>
    <edge source="49" target="60">
      <data key="d0">0.281537</data>
    </edge>
    <edge source="49" target="61">
      <data key="d0">0.563331</data>
    </edge>
    <edge source="49" target="65">
      <data key="d0">0.487124</data>
    </edge>
    <edge source="49" target="68">
      <data key="d0">0.497662</data>
    </edge>
    <edge source="49" target="72">
      <data key="d0">0.475838</data>
    </edge>
    <edge source="49" target="73">
      <data key="d0">0.318066</data>
    </edge>
    <edge source="49" target="74">
      <data key="d0">0.47555</data>
    </edge>
    <edge source="49" target="77">
      <data key="d0">0.459527</data>
    </edge>
    <edge source="49" target="78">
      <data key="d0">0.0956195</data>
    </edge>
    <edge source="49" target="79">
      <data key="d0">0.421098</data>
    </edge>
    <edge source="49" target="80">
      <data key="d0">0.437278</data>
    </edge>
    <edge source="49" target="83">
      <data key="d0">0.360604</data>
    </edge>
    <edge source="49" target="84">
      <data key="d0">0.509965</data>
    </edge>
    <edge source="50" target="59">
      <data key="d0">0.515082</data>
    </edge>
    <edge source="50" target="60">
      <data key="d0">0.297641</data>
    </edge>
    <edge source="50" target="65">
      <data key="d0">0.512986</data>
    </edge>
    <edge source="50" target="73">
      <data key="d0">0.443019</data>
    </edge>
    <edge source="50" target="78">
      <data key="d0">0.300487</data>
    </edge>
    <edge source="50" target="79">
      <data key="d0">0.52643</data>
    </edge>
    <edge source="50" target="83">
      <data key="d0">0.457193</data>
    </edge>
    <edge source="51" target="59">
      <data key="d0">0.512716</data>
    </edge>
    <edge source="51" target="60">
      <data key="d0">0.404418</data>
    </edge>
    <edge source="51" target="68">
      <data key="d0">0.588754</data>
    </edge>
    <edge source="51" target="72">
      <data key="d0">0.546902</data>
    </edge>
    <edge source="51" target="73">
      <data key="d0">0.337936</data>
    </edge>
    <edge source="51" target="78">
      <data key="d0">0.3153</data>
    </edge>
    <edge source="51" target="80">
      <data key="d0">0.467318</data>
    </edge>
    <edge source="51" target="83">
      <data key="d0">0.508582</data>
    </edge>
    <edge source="51" target="84">
      <data key="d0">0.547528</data>
    </edge>
    <edge source="52" target="59">
      <data key="d0">0.590025</data>
    </edge>
    <edge source="52" target="60">
      <data key="d0">0.300958</data>
    </edge>
    <edge source="52" target="73">
      <data key="d0">0.268935</data>
    </edge>
    <edge source="52" target="78">
      <data key="d0">0.241622</data>
    </edge>
    <edge source="52" target="83">
      <data key="d0">0.47166</data>
    </edge>
    <edge source="53" target="59">
      <data key="d0">0.590748</data>
    </edge>
    <edge source="53" target="60">
      <data key="d0">0.248087</data>
    </edge>
    <edge source="53" target="72">
      <data key="d0">0.528483</data>
    </edge>
    <edge source="53" target="73">
      <data key="d0">0.353221</data>
    </edge>
    <edge source="53" target="78">
      <data key="d0">0.391476</data>
    </edge>
    <edge source="53" target="83">
      <data key="d0">0.48552</data>
    </edge>
    <edge source="54" target="59">
      <data key="d0">0.549508</data>
    </edge>
    <edge source="54" target="60">
      <data key="d0">0.290392</data>
    </edge>
    <edge source="54" target="73">
      <data key="d0">0.367732</data>
    </edge>
    <edge source="54" target="78">
      <data key="d0">0.368942</data>
    </edge>
    <edge source="54" target="83">
      <data key="d0">0.453574</data>
    </edge>
    <edge source="55" target="59">
      <data key="d0">0.521994</data>
    </edge>
    <edge source="55" target="60">
      <data key="d0">0.335624</data>
    </edge>
    <edge source="55" target="73">
      <data key="d0">0.2843</data>
    </edge>
    <edge source="55" target="78">
      <data key="d0">0.279281</data>
    </edge>
    <edge source="55" target="79">
      <data key="d0">0.574997</data>
    </edge>
    <edge source="55" target="83">
      <data key="d0">0.45797</data>
    </edge>
    <edge source="56" target="59">
      <data key="d0">0.533602</data>
    </edge>
    <edge source="56" target="60">
      <data key="d0">0.246166</data>
    </edge>
    <edge source="56" target="65">
      <data key="d0">0.549503</data>
    </edge>
    <edge source="56" target="73">
      <data key="d0">0.254791</data>
    </edge>
    <edge source="56" target="74">
      <data key="d0">0.574538</data>
    </edge>
    <edge source="56" target="77">
      <data key="d0">0.593609</data>
    </edge>
    <edge source="56" target="78">
      <data key="d0">0.430024</data>
    </edge>
    <edge source="56" target="80">
      <data key="d0">0.49876</data>
    </edge>
    <edge source="56" target="83">
      <data key="d0">0.527775</data>
    </edge>
    <edge source="57" target="59">
      <data key="d0">0.529709</data>
    </edge>
    <edge source="57" target="60">
      <data key="d0">0.34119</data>
    </edge>
    <edge source="57" target="73">
      <data key="d0">0.264455</data>
    </edge>
    <edge source="57" target="78">
      <data key="d0">0.371728</data>
    </edge>
    <edge source="58" target="59">
      <data key="d0">0.585101</data>
    </edge>
    <edge source="58" target="60">
      <data key="d0">0.378568</data>
    </edge>
    <edge source="58" target="73">
      <data key="d0">0.418364</data>
    </edge>
    <edge source="58" target="78">
      <data key="d0">0.345929</data>
    </edge>
    <edge source="58" target="79">
      <data key="d0">0.583881</data>
    </edge>
    <edge source="58" target="83">
      <data key="d0">0.47825</data>
    </edge>
    <edge source="59" target="60">
      <data key="d0">0.359629</data>
    </edge>
    <edge source="59" target="61">
      <data key="d0">0.467947</data>
    </edge>
    <edge source="59" target="62">
      <data key="d0">0.509323</data>
    </edge>
    <edge source="59" target="63">
      <data key="d0">0.536071</data>
    </edge>
    <edge source="59" target="64">
      <data key="d0">0.502269</data>
    </edge>
    <edge source="59" target="65">
      <data key="d0">0.324208</data>
    </edge>
    <edge source="59" target="66">
      <data key="d0">0.501109</data>
    </edge>
    <edge source="59" target="67">
      <data key="d0">0.534676</data>
    </edge>
    <edge source="59" target="68">
      <data key="d0">0.446983</data>
    </edge>
    <edge source="59" target="69">
      <data key="d0">0.420798</data>
    </edge>
    <edge source="59" target="70">
      <data key="d0">0.487755</data>
    </edge>
    <edge source="59" target="71">
      <data key="d0">0.540674</data>
    </edge>
    <edge source="59" target="72">
      <data key="d0">0.417223</data>
    </edge>
    <edge source="59" target="73">
      <data key="d0">0.160317</data>
    </edge>
    <edge source="59" target="74">
      <data key="d0">0.2296</data>
    </edge>
    <edge source="59" target="75">
      <data key="d0">0.472273</data>
    </edge>
    <edge source="59" target="76">
      <data key="d0">0.474468</data>
    </edge>
    <edge source="59" target="77">
      <data key="d0">0.303184</data>
    </edge>
    <edge source="59" target="78">
      <data key="d0">0.330829</data>
    </edge>
    <edge source="59" target="79">
      <data key="d0">0.440724</data>
    </edge>
    <edge source="59" target="80">
      <data key="d0">0.281515</data>
    </edge>
    <edge source="59" target="81">
      <data key="d0">0.518313</data>
    </edge>
    <edge source="59" target="82">
      <data key="d0">0.479264</data>
    </edge>
    <edge source="59" target="83">
      <data key="d0">0.269758</data>
    </edge>
    <edge source="59" target="84">
      <data key="d0">0.403525</data>
    </edge>
    <edge source="60" target="61">
      <data key="d0">0.136</data>
    </edge>
    <edge source="60" target="62">
      <data key="d0">0.414746</data>
    </edge>
    <edge source="60" target="63">
      <data key="d0">0.430479</data>
    </edge>
    <edge source="60" target="64">
      <data key="d0">0.350404</data>
    </edge>
    <edge source="60" target="65">
      <data key="d0">0.286064</data>
    </edge>
    <edge source="60" target="66">
      <data key="d0">0.377671</data>
    </edge>
    <edge source="60" target="67">
      <data key="d0">0.337683</data>
    </edge>
    <edge source="60" target="68">
      <data key="d0">0.360677</data>
    </edge>
    <edge source="60" target="69">
      <data key="d0">0.205171</data>
    </edge>
    <edge source="60" target="70">
      <data key="d0">0.357307</data>
    </edge>
    <edge source="60" target="71">
      <data key="d0">0.345057</data>
    </edge>
    <edge source="60" target="72">
      <data key="d0">0.291598</data>
    </edge>
    <edge source="60" target="73">
      <data key="d0">0.309634</data>
    </edge>
    <edge source="60" target="74">
      <data key="d0">0.361628</data>
    </edge>
    <edge source="60" target="75">
      <data key="d0">0.322534</data>
    </edge>
    <edge source="60" target="76">
      <data key="d0">0.343856</data>
    </edge>
    <edge source="60" target="77">
      <data key="d0">0.479664</data>
    </edge>
    <edge source="60" target="78">
      <data key="d0">0.222724</data>
    </edge>
    <edge source="60" target="79">
      <data key="d0">0.172171</data>
    </edge>
    <edge source="60" target="80">
      <data key="d0">0.318335</data>
    </edge>
    <edge source="60" target="81">
      <data key="d0">0.290085</data>
    </edge>
    <edge source="60" target="82">
      <data key="d0">0.281413</data>
    </edge>
    <edge source="60" target="83">
      <data key="d0">0.144076</data>
    </edge>
    <edge source="60" target="84">
      <data key="d0">0.0825848</data>
    </edge>
    <edge source="61" target="65">
      <data key="d0">0.562803</data>
    </edge>
    <edge source="61" target="68">
      <data key="d0">0.580695</data>
    </edge>
    <edge source="61" target="72">
      <data key="d0">0.475632</data>
    </edge>
    <edge source="61" target="73">
      <data key="d0">0.244968</data>
    </edge>
    <edge source="61" target="77">
      <data key="d0">0.534328</data>
    </edge>
    <edge source="61" target="78">
      <data key="d0">0.359833</data>
    </edge>
    <edge source="61" target="80">
      <data key="d0">0.590433</data>
    </edge>
    <edge source="62" target="65">
      <data key="d0">0.594637</data>
    </edge>
    <edge source="62" target="73">
      <data key="d0">0.377825</data>
    </edge>
    <edge source="62" target="78">
      <data key="d0">0.373419</data>
    </edge>
    <edge source="62" target="83">
      <data key="d0">0.509597</data>
    </edge>
    <edge source="62" target="84">
      <data key="d0">0.508593</data>
    </edge>
    <edge source="63" target="73">
      <data key="d0">0.289314</data>
    </edge>
    <edge source="63" target="78">
      <data key="d0">0.385553</data>
    </edge>
    <edge source="63" target="83">
      <data key="d0">0.575887</data>
    </edge>
    <edge source="64" target="73">
      <data key="d0">0.364459</data>
    </edge>
    <edge source="64" target="78">
      <data key="d0">0.329022</data>
    </edge>
    <edge source="64" target="83">
      <data key="d0">0.48622</data>
    </edge>
    <edge source="65" target="66">
      <data key="d0">0.540819</data>
    </edge>
    <edge source="65" target="68">
      <data key="d0">0.544186</data>
    </edge>
    <edge source="65" target="72">
      <data key="d0">0.574556</data>
    </edge>
    <edge source="65" target="73">
      <data key="d0">0.158056</data>
    </edge>
    <edge source="65" target="77">
      <data key="d0">0.498851</data>
    </edge>
    <edge source="65" target="78">
      <data key="d0">0.376784</data>
    </edge>
    <edge source="65" target="79">
      <data key="d0">0.563582</data>
    </edge>
    <edge source="65" target="83">
      <data key="d0">0.363934</data>
    </edge>
    <edge source="65" target="84">
      <data key="d0">0.483944</data>
    </edge>
    <edge source="66" target="73">
      <data key="d0">0.268277</data>
    </edge>
    <edge source="66" target="78">
      <data key="d0">0.281658</data>
    </edge>
    <edge source="66" target="83">
      <data key="d0">0.427595</data>
    </edge>
    <edge source="67" target="73">
      <data key="d0">0.343432</data>
    </edge>
    <edge source="67" target="78">
      <data key="d0">0.347775</data>
    </edge>
    <edge source="67" target="83">
      <data key="d0">0.481972</data>
    </edge>
    <edge source="68" target="73">
      <data key="d0">0.123908</data>
    </edge>
    <edge source="68" target="74">
      <data key="d0">0.574582</data>
    </edge>
    <edge source="68" target="78">
      <data key="d0">0.491011</data>
    </edge>
    <edge source="68" target="79">
      <data key="d0">0.52279</data>
    </edge>
    <edge source="68" target="80">
      <data key="d0">0.533374</data>
    </edge>
    <edge source="68" target="83">
      <data key="d0">0.472843</data>
    </edge>
    <edge source="69" target="73">
      <data key="d0">0.238378</data>
    </edge>
    <edge source="69" target="78">
      <data key="d0">0.19197</data>
    </edge>
    <edge source="69" target="83">
      <data key="d0">0.494588</data>
    </edge>
    <edge source="70" target="73">
      <data key="d0">0.304346</data>
    </edge>
    <edge source="70" target="78">
      <data key="d0">0.385877</data>
    </edge>
    <edge source="71" target="73">
      <data key="d0">0.132039</data>
    </edge>
    <edge source="71" target="78">
      <data key="d0">0.350165</data>
    </edge>
    <edge source="71" target="83">
      <data key="d0">0.516175</data>
    </edge>
    <edge source="72" target="73">
      <data key="d0">0.292587</data>
    </edge>
    <edge source="72" target="74">
      <data key="d0">0.413514</data>
    </edge>
    <edge source="72" target="77">
      <data key="d0">0.460789</data>
    </edge>
    <edge source="72" target="78">
      <data key="d0">0.295272</data>
    </edge>
    <edge source="72" target="79">
      <data key="d0">0.465576</data>
    </edge>
    <edge source="72" target="80">
      <data key="d0">0.545343</data>
    </edge>
    <edge source="72" target="83">
      <data key="d0">0.463452</data>
    </edge>
    <edge source="73" target="74">
      <data key="d0">0.121786</data>
    </edge>
    <edge source="73" target="75">
      <data key="d0">0.297922</data>
    </edge>
    <edge source="73" target="76">
      <data key="d0">0.414536</data>
    </edge>
    <edge source="73" target="77">
      <data key="d0">0.487935</data>
    </edge>
    <edge source="73" target="78">
      <data key="d0">0.0367565</data>
    </edge>
    <edge source="73" target="79">
      <data key="d0">0.0101267</data>
    </edge>
    <edge source="73" target="80">
      <data key="d0">0.287408</data>
    </edge>
    <edge source="73" target="81">
      <data key="d0">0.340615</data>
    </edge>
    <edge source="73" target="82">
      <data key="d0">0.358626</data>
    </edge>
    <edge source="73" target="83">
      <data key="d0">0.17847</data>
    </edge>
    <edge source="73" target="84">
      <data key="d0">0.308994</data>
    </edge>
    <edge source="74" target="78">
      <data key="d0">0.234705</data>
    </edge>
    <edge source="74" target="83">
      <data key="d0">0.407707</data>
    </edge>
    <edge source="74" target="84">
      <data key="d0">0.407227</data>
    </edge>
    <edge source="75" target="78">
      <data key="d0">0.279789</data>
    </edge>
    <edge source="75" target="83">
      <data key="d0">0.413615</data>
    </edge>
    <edge source="75" target="84">
      <data key="d0">0.576294</data>
    </edge>
    <edge source="76" target="78">
      <data key="d0">0.374328</data>
    </edge>
    <edge source="76" target="83">
      <data key="d0">0.493026</data>
    </edge>
    <edge source="77" target="78">
      <data key="d0">0.309429</data>
    </edge>
    <edge source="77" target="79">
      <data key="d0">0.433039</data>
    </edge>
    <edge source="77" target="80">
      <data key="d0">0.545559</data>
    </edge>
    <edge source="77" target="83">
      <data key="d0">0.405613</data>
    </edge>
    <edge source="77" target="84">
      <data key="d0">0.553034</data>
    </edge>
    <edge source="78" target="79">
      <data key="d0">0.4802</data>
    </edge>
    <edge source="78" target="80">
      <data key="d0">0.174597</data>
    </edge>
    <edge source="78" target="81">
      <data key="d0">0.290178</data>
    </edge>
    <edge source="78" target="82">
      <data key="d0">0.337292</data>
    </edge>
    <edge source="78" target="83">
      <data key="d0">0.442976</data>
    </edge>
    <edge source="78" target="84">
      <data key="d0">0.305029</data>
    </edge>
    <edge source="79" target="80">
      <data key="d0">0.409684</data>
    </edge>
    <edge source="79" target="83">
      <data key="d0">0.451179</data>
    </edge>
    <edge source="79" target="84">
      <data key="d0">0.439543</data>
    </edge>
    <edge source="80" target="83">
      <data key="d0">0.346308</data>
    </edge>
    <edge source="80" target="84">
      <data key="d0">0.526881</data>
    </edge>
    <edge source="81" target="83">
      <data key="d0">0.475144</data>
    </edge>
    <edge source="82" target="83">
      <data key="d0">0.530714</data>
    </edge>
    <edge source="83" target="84">
      <data key="d0">0.515845</data>
    </edge>
  </graph>
</graphml>
